relativistic_adam/__init__.py
relativistic_adam/optimizer.py
relativistic_adam-1.0.0.dist-info/licenses/LICENSE
relativistic_adam-1.0.0.dist-info/METADATA
relativistic_adam-1.0.0.dist-info/WHEEL
relativistic_adam-1.0.0.dist-info/top_level.txt
relativistic_adam-1.0.0.dist-info/RECORD
