Metadata-Version: 2.4
Name: relativistic-adam
Version: 1.0.0
Summary: A PyTorch optimizer that implements a relativistic gradient clipping mechanism, inspired by the theory of special relativity
Author: Souradeep Nanda
Maintainer: Souradeep Nanda
License: MIT
Project-URL: Homepage, https://github.com/Ghost---Shadow/relativistic-adam
Project-URL: Repository, https://github.com/Ghost---Shadow/relativistic-adam
Project-URL: Bug Tracker, https://github.com/Ghost---Shadow/relativistic-adam/issues
Project-URL: Documentation, https://github.com/Ghost---Shadow/relativistic-adam#readme
Keywords: pytorch,optimizer,machine-learning,deep-learning,gradient-clipping,physics-inspired,adam,relativity
Classifier: Development Status :: 4 - Beta
Classifier: Intended Audience :: Developers
Classifier: Intended Audience :: Science/Research
Classifier: License :: OSI Approved :: MIT License
Classifier: Programming Language :: Python :: 3
Classifier: Programming Language :: Python :: 3.7
Classifier: Programming Language :: Python :: 3.8
Classifier: Programming Language :: Python :: 3.9
Classifier: Programming Language :: Python :: 3.10
Classifier: Programming Language :: Python :: 3.11
Classifier: Programming Language :: Python :: 3.12
Classifier: Topic :: Scientific/Engineering :: Artificial Intelligence
Classifier: Topic :: Software Development :: Libraries :: Python Modules
Requires-Python: >=3.7
License-File: LICENSE
Requires-Dist: torch>=1.9.0
Provides-Extra: dev
Requires-Dist: pytest>=6.0; extra == "dev"
Requires-Dist: black; extra == "dev"
Requires-Dist: isort; extra == "dev"
Requires-Dist: flake8; extra == "dev"
Requires-Dist: mypy; extra == "dev"
Provides-Extra: test
Requires-Dist: pytest>=6.0; extra == "test"
Dynamic: license-file
